hkdm/__init__.py
hkdm/backends.py
hkdm/cache.py
hkdm/cli.py
hkdm/commands.py
hkdm/configuration.py
hkdm/interactive.py
hkdm/legacy_backends.py
hkdm/maid.py
hkdm/storage.py
hkdm/tests.py
hkdm/utils.py
hkdm-1.9.0.dist-info/LICENSE
hkdm-1.9.0.dist-info/METADATA
hkdm-1.9.0.dist-info/WHEEL
hkdm-1.9.0.dist-info/entry_points.txt
hkdm-1.9.0.dist-info/top_level.txt
hkdm-1.9.0.dist-info/zip-safe
hkdm-1.9.0.dist-info/RECORD
