Metadata-Version: 2.1
Name: hkdm
Version: 1.9.0
Summary: HyperK Data Manager
Home-page: https://github.com/t2k-software/t2kdm
Author: Lukas Koch
Author-email: lukas.koch@mailbox.org
License: MIT
Platform: UNKNOWN
Classifier: Development Status :: 5 - Production/Stable
Classifier: Intended Audience :: Developers
Classifier: Intended Audience :: Science/Research
Classifier: Topic :: Scientific/Engineering
Classifier: License :: OSI Approved :: MIT License
Classifier: Programming Language :: Python :: 2
Classifier: Programming Language :: Python :: 2.6
Classifier: Programming Language :: Python :: 2.7
Requires-Python: >=2.6
Requires-Dist: sh (>=1.12.14)
Requires-Dist: six (>=1.10.0)
Requires-Dist: appdirs (>=1.4.3)
